{
    "resource_source": {
        "resource": [
            "NovelKit/ProductAdvObjectBg",
            "NovelKit/ProductAdvObject2D",
            "NovelKit/ProductAdvObject2DSub",
            "NovelKit/ProductAdvObjectCg"
        ],
        "sound": [],
        "script": [],
        "definition": [
            "Scenarios/ConstantValues/llas_constants",
            "Scenarios/ConstantValues/llas_character_constants",
            "Scenarios/ConstantValues/llas_bg_constants",
            "Scenarios/ConstantValues/llas_sound_constants",
            "Scenarios/ConstantValues/llas_character_preset",
            "Scenarios/ConstantValues/llas_character_facial"
        ]
    },
    "preload": {
        "ui": [
            "label|0|1|2|3|4"
        ],
        "icon": [
            "aqours|5|6|7|8|9|10|11|12|13|14|15|16"
        ],
        "ch": [
            "109 22001 1|17|18",
            "109 22001 2|17|18",
            "109 22001 5|17|18",
            "109 22001 4|17|18"
        ],
        "bg": [
            "20"
        ],
        "cg": [
            "19"
        ],
        "sp": [],
        "phoneicon": []
    },
    "markers": {
        "jump": {},
        "other": {}
    },
    "commands": [
        {
            "command": "fade",
            "direction": "out",
            "side": "front",
            "duration": "0"
        },
        {
            "command": "set_viewing",
            "viewing_value": "enable"
        },
        {
            "command": "wait_for_load"
        },
        {
            "command": "background",
            "background_id": "1",
            "background_cmd": "load",
            "load_args": "default|20"
        },
        {
            "command": "background",
            "background_id": "2",
            "background_cmd": "load",
            "load_args": "default|20"
        },
        {
            "command": "background",
            "background_id": "2",
            "background_cmd": "scale",
            "scale_x": 1.2,
            "scale_y": 1.2
        },
        {
            "command": "background",
            "background_id": "2",
            "background_cmd": "hide"
        },
        {
            "command": "music",
            "fade": true,
            "args": "out 1.0"
        },
        {
            "command": "sound",
            "args": "bgm 0"
        },
        {
            "command": "character",
            "character_id": "1",
            "character_cmd": "create"
        },
        {
            "command": "character",
            "character_id": "1",
            "character_cmd": "visual",
            "visual_character": "",
            "visual_outfit": "109",
            "visual_expression": "22001"
        },
        {
            "command": "character",
            "character_id": "1",
            "character_cmd": "pos",
            "pos_x": "0",
            "pos_y": "-40"
        },
        {
            "command": "wait",
            "duration": 0.2
        },
        {
            "command": "set_fade_setting",
            "fade_settings": "type Slanting"
        },
        {
            "command": "fade",
            "direction": "in",
            "side": "front",
            "duration": "0.5"
        },
        {
            "command": "wait",
            "duration": 0.2
        },
        {
            "command": "set_viewing",
            "viewing_value": "disable"
        },
        {
            "command": "character",
            "character_id": "1",
            "character_cmd": "shake",
            "character_args": [
                "x",
                "3",
                "7"
            ]
        },
        {
            "command": "wait",
            "duration": 0.2
        },
        {
            "command": "character",
            "character_id": "1",
            "character_cmd": "talk"
        },
        {
            "command": "speak",
            "speaker": "Ruby",
            "line": "This... Wait, no, maybe that one.",
            "voice_idx": "1",
            "is_plus": true
        },
        {
            "command": "delay",
            "duration": 0.4
        },
        {
            "command": "character",
            "character_id": "1",
            "character_cmd": "stopshake",
            "character_args": []
        },
        {
            "command": "end_delay"
        },
        {
            "command": "wait_for_click"
        },
        {
            "command": "speak",
            "speaker": "[player]",
            "line": "Ruby, we've basically got all the costume materials that were on the list.",
            "voice_idx": null,
            "is_plus": false
        },
        {
            "command": "character",
            "character_id": "1",
            "character_cmd": "face",
            "visual_expression": "1"
        },
        {
            "command": "character",
            "character_id": "1",
            "character_cmd": "talk"
        },
        {
            "command": "speak",
            "speaker": "Ruby",
            "line": "Oh, thanks. Sorry, I can't make up my mind. Just give me a bit longer.",
            "voice_idx": "2",
            "is_plus": false
        },
        {
            "command": "speak",
            "speaker": "[player]",
            "line": "No problem, there's no rush. But you sure look serious. What are you shopping for?",
            "voice_idx": null,
            "is_plus": false
        },
        {
            "command": "character",
            "character_id": "1",
            "character_cmd": "face",
            "visual_expression": "2"
        },
        {
            "command": "character",
            "character_id": "1",
            "character_cmd": "talk"
        },
        {
            "command": "speak",
            "speaker": "Ruby",
            "line": "Ribbons.",
            "voice_idx": "3",
            "is_plus": false
        },
        {
            "command": "speak",
            "speaker": "[player]",
            "line": "Ribbons?",
            "voice_idx": null,
            "is_plus": false
        },
        {
            "command": "character",
            "character_id": "1",
            "character_cmd": "face",
            "visual_expression": "1"
        },
        {
            "command": "character",
            "character_id": "1",
            "character_cmd": "talk"
        },
        {
            "command": "speak",
            "speaker": "Ruby",
            "line": "Yeah. There are all kinds of ribbons you can buy, in all different colors and materials. The material of the ribbon can completely change the impression a costume gives.",
            "voice_idx": "4",
            "is_plus": true
        },
        {
            "command": "delay",
            "duration": 0.1
        },
        {
            "command": "character",
            "character_id": "1",
            "character_cmd": "nod",
            "character_args": [
                "-10"
            ]
        },
        {
            "command": "end_delay"
        },
        {
            "command": "wait_for_click"
        },
        {
            "command": "speak",
            "speaker": "[player]",
            "line": "Wow, you're right. There's satin, lace... Oh, this one's cute! Polka dots!",
            "voice_idx": null,
            "is_plus": false
        },
        {
            "command": "character",
            "character_id": "1",
            "character_cmd": "face",
            "visual_expression": "2"
        },
        {
            "command": "character",
            "character_id": "1",
            "character_cmd": "talk"
        },
        {
            "command": "speak",
            "speaker": "Ruby",
            "line": "I'm using the stuff we're buying today to make new costumes, but they need ribbon, too. I just can't settle on anything, though.",
            "voice_idx": "5",
            "is_plus": false
        },
        {
            "command": "character",
            "character_id": "1",
            "character_cmd": "face",
            "visual_expression": "1"
        },
        {
            "command": "character",
            "character_id": "1",
            "character_cmd": "talk"
        },
        {
            "command": "speak",
            "speaker": "Ruby",
            "line": "All nine of us have a different costume, but the costumes are all based on the same concept.",
            "voice_idx": "6",
            "is_plus": false
        },
        {
            "command": "character",
            "character_id": "1",
            "character_cmd": "eye",
            "visual_eyes": "close"
        },
        {
            "command": "wait",
            "duration": 0.2
        },
        {
            "command": "character",
            "character_id": "1",
            "character_cmd": "talk"
        },
        {
            "command": "speak",
            "speaker": "Ruby",
            "line": "Should I use the same ribbon for all of them? Or differentiate each costume with smaller details, and choose a unique ribbon that matches each person's personality?",
            "voice_idx": "7",
            "is_plus": false
        },
        {
            "command": "character",
            "character_id": "1",
            "character_cmd": "eye",
            "visual_eyes": "open"
        },
        {
            "command": "wait",
            "duration": 0.2
        },
        {
            "command": "speak",
            "speaker": "[player]",
            "line": "Ruby, you really take every last thing into account when you make costumes, don't you?",
            "voice_idx": null,
            "is_plus": false
        },
        {
            "command": "character",
            "character_id": "1",
            "character_cmd": "face",
            "visual_expression": "4"
        },
        {
            "command": "character",
            "character_id": "1",
            "character_cmd": "jump"
        },
        {
            "command": "wait",
            "duration": 0.2
        },
        {
            "command": "character",
            "character_id": "1",
            "character_cmd": "talk"
        },
        {
            "command": "speak",
            "speaker": "Ruby",
            "line": "Eep! I-I-I-I'm sorry! All I'm doing is wringing my hands. I should just pick something and not look back!",
            "voice_idx": "8",
            "is_plus": false
        },
        {
            "command": "speak",
            "speaker": "[player]",
            "line": "No, no. It's okay. With this being for everyone's costumes, I don't blame you for weighing your options carefully. It'll make them that much more beautiful in the end, right?",
            "voice_idx": null,
            "is_plus": false
        },
        {
            "command": "character",
            "character_id": "1",
            "character_cmd": "face",
            "visual_expression": "1"
        },
        {
            "command": "character",
            "character_id": "1",
            "character_cmd": "talk"
        },
        {
            "command": "speak",
            "speaker": "Ruby",
            "line": "Yeah. I want to make the best costumes I can, so I have to be a real stickler for details.",
            "voice_idx": "9",
            "is_plus": false
        },
        {
            "command": "character",
            "character_id": "1",
            "character_cmd": "hide"
        },
        {
            "command": "background",
            "background_id": "2",
            "background_cmd": "show"
        },
        {
            "command": "character",
            "character_id": "2",
            "character_cmd": "create"
        },
        {
            "command": "character",
            "character_id": "2",
            "character_cmd": "visual",
            "visual_character": "",
            "visual_outfit": "109",
            "visual_expression": "22001"
        },
        {
            "command": "character",
            "character_id": "2",
            "character_cmd": "pos",
            "pos_x": "0",
            "pos_y": "-40"
        },
        {
            "command": "character",
            "character_id": "2",
            "character_cmd": "scale",
            "scale_x": 1.2,
            "scale_y": 1.2
        },
        {
            "command": "character",
            "character_id": "2",
            "character_cmd": "pos",
            "pos_x": "/0",
            "pos_y": "/-45"
        },
        {
            "command": "character",
            "character_id": "2",
            "character_cmd": "show"
        },
        {
            "command": "wait",
            "duration": 0.5
        },
        {
            "command": "speak",
            "speaker": "[player]",
            "line": "You don't have to do it all by yourself, though. Maybe I can help you pick out your ribbon! I want to see the members of Aqours wear beautiful costumes just as much as you.",
            "voice_idx": null,
            "is_plus": false
        },
        {
            "command": "character",
            "character_id": "2",
            "character_cmd": "face",
            "visual_expression": "2"
        },
        {
            "command": "character",
            "character_id": "2",
            "character_cmd": "jump"
        },
        {
            "command": "wait",
            "duration": 0.2
        },
        {
            "command": "character",
            "character_id": "2",
            "character_cmd": "talk"
        },
        {
            "command": "speak",
            "speaker": "Ruby",
            "line": "Really? Thank you!",
            "voice_idx": "10",
            "is_plus": false
        },
        {
            "command": "speak",
            "speaker": "[player]",
            "line": "So, which ones are your top candidates so far?",
            "voice_idx": null,
            "is_plus": false
        },
        {
            "command": "set_viewing",
            "viewing_value": "enable"
        },
        {
            "command": "set_fade_setting",
            "fade_settings": "flip disable"
        },
        {
            "command": "set_fade_setting",
            "fade_settings": "type SlimStripeHorizontal"
        },
        {
            "command": "fade",
            "direction": "out",
            "side": "front",
            "duration": "0.5"
        },
        {
            "command": "unknown_cg",
            "cg_arg": "1 load card|19"
        },
        {
            "command": "wait",
            "duration": 0.2
        },
        {
            "command": "set_fade_setting",
            "fade_settings": "flip enable"
        },
        {
            "command": "set_fade_setting",
            "fade_settings": "type SlimStripeHorizontal"
        },
        {
            "command": "fade",
            "direction": "in",
            "side": "front",
            "duration": "0.5"
        },
        {
            "command": "wait",
            "duration": 0.3
        },
        {
            "command": "set_viewing",
            "viewing_value": "disable"
        },
        {
            "command": "character",
            "character_id": "2",
            "character_cmd": "talk"
        },
        {
            "command": "speak",
            "speaker": "Ruby",
            "line": "Just a sec. Okay, this pink satin one, this striped one, this one, that one... Oh, and this, this, this, and...",
            "voice_idx": "11",
            "is_plus": false
        },
        {
            "command": "speak",
            "speaker": "[player]",
            "line": "Whoa, that's a lot to go through. But it'll be worth it in the end!",
            "voice_idx": null,
            "is_plus": false
        },
        {
            "command": "set_fade_setting",
            "fade_settings": "type Default"
        },
        {
            "command": "fade",
            "direction": "out",
            "side": "front",
            "duration": "0.5"
        }
    ]
}