{
    "resource_source": {
        "resource": [
            "NovelKit/ProductAdvObjectBg",
            "NovelKit/ProductAdvObjectEffect",
            "NovelKit/Effects/Prefabs/fx_adventure_effects_placeview_02",
            "NovelKit/ProductAdvObject2D",
            "NovelKit/ProductAdvObject2DSub",
            "NovelKit/ProductAdvObjectCg"
        ],
        "sound": [],
        "script": [],
        "definition": [
            "Scenarios/ConstantValues/llas_constants",
            "Scenarios/ConstantValues/llas_character_constants",
            "Scenarios/ConstantValues/llas_bg_constants",
            "Scenarios/ConstantValues/llas_sound_constants",
            "Scenarios/ConstantValues/llas_character_preset",
            "Scenarios/ConstantValues/llas_character_facial"
        ]
    },
    "preload": {
        "ui": [
            "label|0|1|2|3|4"
        ],
        "icon": [
            "muse|5|6|7|8|9|10|11|12|13|14|15|16",
            "aqours|17|18|19|20|21|22|23|24|25|14|26|16",
            "niji|27|28|29|30|31|32|33|34|35|36|14|37|16"
        ],
        "ch": [
            "1 22001 1|38|39",
            "1 22001 2|38|39",
            "1 22001 5|38|39",
            "1 22001 4|38|39"
        ],
        "bg": [
            "40",
            "41"
        ],
        "cg": [
            "42"
        ],
        "sp": [],
        "phoneicon": []
    },
    "markers": {
        "jump": {},
        "other": {}
    },
    "commands": [
        {
            "command": "fade",
            "direction": "out",
            "side": "front",
            "duration": "0"
        },
        {
            "command": "set_viewing",
            "viewing_value": "enable"
        },
        {
            "command": "wait_for_load"
        },
        {
            "command": "background",
            "background_id": "2",
            "background_cmd": "load",
            "load_args": "default|40"
        },
        {
            "command": "music",
            "fade": true,
            "args": "out 1.0"
        },
        {
            "command": "sound",
            "args": "bgm 0"
        },
        {
            "command": "set_fade_setting",
            "fade_settings": "type Slanting"
        },
        {
            "command": "fade",
            "direction": "in",
            "side": "front",
            "duration": "0.5"
        },
        {
            "command": "wait",
            "duration": 0.2
        },
        {
            "command": "unknown_ef",
            "ef_arg": "1 load place"
        },
        {
            "command": "unknown_ef",
            "ef_arg": "1 plane 1"
        },
        {
            "command": "unknown_ef",
            "ef_arg": "1 option window off"
        },
        {
            "command": "unknown_ef",
            "ef_arg": "1 play ||Homura Bakery||"
        },
        {
            "command": "wait",
            "duration": 0.3
        },
        {
            "command": "unknown_ef",
            "ef_arg": "1 hide"
        },
        {
            "command": "wait",
            "duration": 0.2
        },
        {
            "command": "sound",
            "args": "se 1"
        },
        {
            "command": "set_fade_setting",
            "fade_settings": "type Horizontal"
        },
        {
            "command": "set_fade_setting",
            "fade_settings": "flip disable"
        },
        {
            "command": "fade",
            "direction": "out",
            "side": "front",
            "duration": "0.5"
        },
        {
            "command": "background",
            "background_id": "2",
            "background_cmd": "hide"
        },
        {
            "command": "background",
            "background_id": "1",
            "background_cmd": "load",
            "load_args": "default|41"
        },
        {
            "command": "wait",
            "duration": 0.3
        },
        {
            "command": "set_fade_setting",
            "fade_settings": "type Horizontal"
        },
        {
            "command": "set_fade_setting",
            "fade_settings": "flip enable"
        },
        {
            "command": "fade",
            "direction": "in",
            "side": "front",
            "duration": "0.5"
        },
        {
            "command": "wait",
            "duration": 0.5
        },
        {
            "command": "character",
            "character_id": "1",
            "character_cmd": "create"
        },
        {
            "command": "character",
            "character_id": "1",
            "character_cmd": "visual",
            "visual_character": "1",
            "visual_outfit": "22001"
        },
        {
            "command": "character",
            "character_id": "1",
            "character_cmd": "face",
            "visual_expression": "2"
        },
        {
            "command": "character",
            "character_id": "1",
            "character_cmd": "pos",
            "pos_x": "0",
            "pos_y": "-40"
        },
        {
            "command": "character",
            "character_id": "1",
            "character_cmd": "pos",
            "pos_x": "/-10",
            "pos_y": "/0"
        },
        {
            "command": "character",
            "character_id": "1",
            "character_cmd": "move",
            "move_args": [
                "-",
                "-",
                "0.3",
                "/10",
                "/0"
            ]
        },
        {
            "command": "character",
            "character_id": "1",
            "character_cmd": "show"
        },
        {
            "command": "wait",
            "duration": 0.4
        },
        {
            "command": "set_viewing",
            "viewing_value": "disable"
        },
        {
            "command": "character",
            "character_id": "1",
            "character_cmd": "talk"
        },
        {
            "command": "speak",
            "speaker": "Honoka",
            "line": "Welcome! Oh, it's just you! Don't startle me like that. What are you up to today?",
            "voice_idx": "2",
            "is_plus": true
        },
        {
            "command": "delay",
            "duration": 1.5
        },
        {
            "command": "character",
            "character_id": "1",
            "character_cmd": "face",
            "visual_expression": "5"
        },
        {
            "command": "character",
            "character_id": "1",
            "character_cmd": "jump"
        },
        {
            "command": "end_delay"
        },
        {
            "command": "wait_for_click"
        },
        {
            "command": "character",
            "character_id": "1",
            "character_cmd": "face",
            "visual_expression": "1"
        },
        {
            "command": "speak",
            "speaker": "[player]",
            "line": "I had some business nearby, so I thought I should get something for the girls over at Nijigasaki on the way back.",
            "voice_idx": null,
            "is_plus": false
        },
        {
            "command": "character",
            "character_id": "1",
            "character_cmd": "face",
            "visual_expression": "2"
        },
        {
            "command": "character",
            "character_id": "1",
            "character_cmd": "talk"
        },
        {
            "command": "speak",
            "speaker": "Honoka",
            "line": "I see.",
            "voice_idx": "3",
            "is_plus": false
        },
        {
            "command": "speak",
            "speaker": "[player]",
            "line": "I didn't think I'd bump into you, though. That's nice of you to help out with your family business.",
            "voice_idx": null,
            "is_plus": false
        },
        {
            "command": "character",
            "character_id": "1",
            "character_cmd": "face",
            "visual_expression": "1"
        },
        {
            "command": "character",
            "character_id": "1",
            "character_cmd": "jump"
        },
        {
            "command": "wait",
            "duration": 0.3
        },
        {
            "command": "character",
            "character_id": "1",
            "character_cmd": "talk"
        },
        {
            "command": "speak",
            "speaker": "Honoka",
            "line": "I'd love to agree, but it's not nice at all.",
            "voice_idx": "4",
            "is_plus": true
        },
        {
            "command": "delay",
            "duration": 1.5
        },
        {
            "command": "character",
            "character_id": "1",
            "character_cmd": "face",
            "visual_expression": "4"
        },
        {
            "command": "end_delay"
        },
        {
            "command": "wait_for_click"
        },
        {
            "command": "speak",
            "speaker": "[player]",
            "line": "What do you mean?",
            "voice_idx": null,
            "is_plus": false
        },
        {
            "command": "character",
            "character_id": "1",
            "character_cmd": "eye",
            "visual_eyes": "close"
        },
        {
            "command": "wait",
            "duration": 0.3
        },
        {
            "command": "character",
            "character_id": "1",
            "character_cmd": "talk"
        },
        {
            "command": "speak",
            "speaker": "Honoka",
            "line": "My pop quiz results were kinda... So I'm taking care of the store as punishment.",
            "voice_idx": "5",
            "is_plus": false
        },
        {
            "command": "speak",
            "speaker": "[player]",
            "line": "O-Oh, I see. Would you mind if I ask about the score you got?",
            "voice_idx": null,
            "is_plus": false
        },
        {
            "command": "character",
            "character_id": "1",
            "character_cmd": "face",
            "visual_expression": "1"
        },
        {
            "command": "character",
            "character_id": "1",
            "character_cmd": "shake",
            "character_args": [
                "x",
                "3",
                "6"
            ]
        },
        {
            "command": "wait",
            "duration": 0.2
        },
        {
            "command": "character",
            "character_id": "1",
            "character_cmd": "talk"
        },
        {
            "command": "speak",
            "speaker": "Honoka",
            "line": "Oh, it's not THAT bad! Ahaha... M-More importantly, what would you like to get?",
            "voice_idx": "6",
            "is_plus": true
        },
        {
            "command": "delay",
            "duration": 0.5
        },
        {
            "command": "character",
            "character_id": "1",
            "character_cmd": "stopshake",
            "character_args": []
        },
        {
            "command": "end_delay"
        },
        {
            "command": "wait_for_click"
        },
        {
            "command": "speak",
            "speaker": "[player]",
            "line": "Hmm... There's so many, I can't choose. Do you have any recommendations, Honoka?",
            "voice_idx": null,
            "is_plus": false
        },
        {
            "command": "set_viewing",
            "viewing_value": "enable"
        },
        {
            "command": "clear"
        },
        {
            "command": "set_fade_setting",
            "fade_settings": "type StripeVertical"
        },
        {
            "command": "set_fade_setting",
            "fade_settings": "flip enable"
        },
        {
            "command": "fade",
            "direction": "out",
            "side": "front",
            "duration": "0.5"
        },
        {
            "command": "unknown_cg",
            "cg_arg": "1 load card|42"
        },
        {
            "command": "wait",
            "duration": 0.3
        },
        {
            "command": "set_fade_setting",
            "fade_settings": "type StripeVertical"
        },
        {
            "command": "set_fade_setting",
            "fade_settings": "flip disable"
        },
        {
            "command": "fade",
            "direction": "in",
            "side": "front",
            "duration": "0.5"
        },
        {
            "command": "wait",
            "duration": 0.3
        },
        {
            "command": "set_viewing",
            "viewing_value": "disable"
        },
        {
            "command": "set_label",
            "label_value": "muse @honoka"
        },
        {
            "command": "speak",
            "speaker": "Honoka",
            "line": "They're all delicious, so it's hard to choose just one. How about this rice cake stuffed with seasonal fruits?",
            "voice_idx": "7",
            "is_plus": false
        },
        {
            "command": "set_label",
            "label_value": "muse @honoka"
        },
        {
            "command": "speak",
            "speaker": "Honoka",
            "line": "Oh, wait! We've recently changed the dough for this red bean wafer, too, and it tastes even better than before!",
            "voice_idx": "8",
            "is_plus": false
        },
        {
            "command": "set_label",
            "label_value": "muse @honoka"
        },
        {
            "command": "speak",
            "speaker": "Honoka",
            "line": "And I can't forget this chestnut dorayaki! I heard that the chestnuts we got this time were extra-large, so it's a great deal...",
            "voice_idx": "9",
            "is_plus": false
        },
        {
            "command": "set_label",
            "label_value": "muse @honoka"
        },
        {
            "command": "speak",
            "speaker": "Honoka",
            "line": "We have red bean jellies with two to three layers, so they look cute and taste awesome!",
            "voice_idx": "10",
            "is_plus": false
        },
        {
            "command": "set_label",
            "label_value": "muse @honoka"
        },
        {
            "command": "speak",
            "speaker": "Honoka",
            "line": "Oh, and also...",
            "voice_idx": "11",
            "is_plus": false
        },
        {
            "command": "speak",
            "speaker": "[player]",
            "line": "Haha, anyone would buy everything recommended by a cheerful, adorable, and lovely shop girl like you.",
            "voice_idx": null,
            "is_plus": false
        },
        {
            "command": "set_label",
            "label_value": "muse @honoka"
        },
        {
            "command": "speak",
            "speaker": "Honoka",
            "line": "N-No way! You're just flattering me.",
            "voice_idx": "12",
            "is_plus": false
        },
        {
            "command": "speak",
            "speaker": "[player]",
            "line": "I'm telling the truth! With you promoting the products, I want them all!",
            "voice_idx": null,
            "is_plus": false
        },
        {
            "command": "set_label",
            "label_value": "muse @honoka"
        },
        {
            "command": "speak",
            "speaker": "Honoka",
            "line": "R-Really? *Giggle* If you buy this set with all of our recommended sweets, I'll throw in some extras for free!",
            "voice_idx": "13",
            "is_plus": false
        },
        {
            "command": "speak",
            "speaker": "[player]",
            "line": "Whoa, if that's the case, I'd have no choice but to buy it.",
            "voice_idx": null,
            "is_plus": false
        },
        {
            "command": "set_label",
            "label_value": "muse @honoka"
        },
        {
            "command": "speak",
            "speaker": "Honoka",
            "line": "Thank you for your purchase! Please come again.",
            "voice_idx": "14",
            "is_plus": false
        },
        {
            "command": "set_fade_setting",
            "fade_settings": "type Default"
        }
    ]
}